api_mqtt/__init__.py
api_mqtt/_version.py
api_mqtt/entities.py
api_mqtt/exceptions.py
api_mqtt/main_loop.py
api_mqtt/mqtt_clients.py
api_mqtt/msg_handlers.py
api_mqtt/publishers.py
api_mqtt/py.typed
api_mqtt/router.py
api_mqtt/usecases.py
sotirr_mqtt_api-1.0.3.dist-info/METADATA
sotirr_mqtt_api-1.0.3.dist-info/WHEEL
sotirr_mqtt_api-1.0.3.dist-info/top_level.txt
sotirr_mqtt_api-1.0.3.dist-info/RECORD
